{
  "date": "2025-09-01",
  "weekday": "一",
  "work_projects": [
    {
      "name": "uclcloud",
      "commits": [
        {
          "hash": "5a07c75c",
          "time": "17:36",
          "message": "fix: 調整雙重密碼驗證邏輯 - 修復測試兼容性",
          "body": ""
        },
        {
          "hash": "3be25f61",
          "time": "17:27",
          "message": "feat: 實現雙重密碼驗證兼容機制",
          "body": "修改登入驗證邏輯，支援 PasswordHash 和 Password 雙重兼容："
        },
        {
          "hash": "57b4fe0e",
          "time": "09:51",
          "message": "fix: 更新 robots.txt 指向動態 sitemap API",
          "body": "- 更新 Sitemap 位置為 /api/sitemap/sitemap.xml"
        },
        {
          "hash": "07dcddba",
          "time": "09:48",
          "message": "feat: 完善 SEO 優化和修復密碼自動升級機制",
          "body": "SEO 優化:"
        }
      ],
      "count": 4
    }
  ],
  "side_projects": [
    {
      "name": "ZebraSite",
      "commits": [
        {
          "hash": "cd551d99",
          "time": "06:33",
          "message": "新增知識庫和認識聯合頁面",
          "body": "- 創建 Knowledge.vue 知識庫頁面，包含月度教育訓練、專業資源、醫學新知三大分類"
        }
      ],
      "count": 1
    }
  ],
  "summary": {
    "workCommits": 4,
    "sideCommits": 1,
    "totalCommits": 5
  }
}